kusto_pandas/__init__.py
kusto_pandas/_render.py
kusto_pandas/dynamic_methods.py
kusto_pandas/kusto_pandas.py
kusto_pandas/magic.py
kusto_pandas/methods.py
kusto_pandas/expression_parser/__init__.py
kusto_pandas/expression_parser/_simple_expression.py
kusto_pandas/expression_parser/aggregates.py
kusto_pandas/expression_parser/arpeggio_parser.py
kusto_pandas/expression_parser/expression_parser.py
kusto_pandas/expression_parser/expression_parser_types.py
kusto_pandas/expression_parser/expression_tree.py
kusto_pandas/expression_parser/kusto_grammar.peg
kusto_pandas/expression_parser/parsimonious_parser.py
kusto_pandas/expression_parser/tabular_operators.py
kusto_pandas/expression_parser/utils.py
kusto_pandas-0.1.0.dist-info/LICENSE
kusto_pandas-0.1.0.dist-info/METADATA
kusto_pandas-0.1.0.dist-info/WHEEL
kusto_pandas-0.1.0.dist-info/top_level.txt
kusto_pandas-0.1.0.dist-info/RECORD
