Metadata-Version: 2.1
Name: kusto-pandas
Version: 0.1.0
Summary: A wrapper around a Pandas DataFrame which allows you to use the syntax of the Kusto Query Language to transform the DataFrame
Home-page: https://github.com/js850/KustoPandas
Author: Jacob Stevenson
License-File: LICENSE
Requires-Dist: parsimonious (==0.8.1)
Requires-Dist: pandas
Requires-Dist: numpy
